mkdocstrings_handlers/_internal/__init__.py
mkdocstrings_handlers/_internal/debug.py
mkdocstrings_handlers/py.typed
mkdocstrings_handlers/python/__init__.py
mkdocstrings_handlers/python/debug.py
mkdocstrings_handlers/python/handler.py
mkdocstrings_handlers/python/rendering.py
mkdocstrings_handlers/python/templates/material/attribute.html
mkdocstrings_handlers/python/templates/material/attributes.html
mkdocstrings_handlers/python/templates/material/children.html
mkdocstrings_handlers/python/templates/material/class.html
mkdocstrings_handlers/python/templates/material/docstring.html
mkdocstrings_handlers/python/templates/material/examples.html
mkdocstrings_handlers/python/templates/material/exceptions.html
mkdocstrings_handlers/python/templates/material/function.html
mkdocstrings_handlers/python/templates/material/keyword_args.html
mkdocstrings_handlers/python/templates/material/method.html
mkdocstrings_handlers/python/templates/material/module.html
mkdocstrings_handlers/python/templates/material/parameters.html
mkdocstrings_handlers/python/templates/material/properties.html
mkdocstrings_handlers/python/templates/material/return.html
mkdocstrings_handlers/python/templates/material/signature.html
mkdocstrings_handlers/python/templates/material/style.css
mkdocstrings_handlers/python/templates/material/yield.html
mkdocstrings_handlers/python/templates/mkdocs/exceptions.html
mkdocstrings_handlers/python/templates/mkdocs/keyword_args.html
mkdocstrings_handlers/python/templates/mkdocs/parameters.html
mkdocstrings_handlers/python/templates/mkdocs/return.html
mkdocstrings_handlers/python/templates/mkdocs/style.css
mkdocstrings_handlers/python/templates/mkdocs/yield.html
mkdocstrings_handlers/python/templates/readthedocs/exceptions.html
mkdocstrings_handlers/python/templates/readthedocs/keyword_args.html
mkdocstrings_handlers/python/templates/readthedocs/parameters.html
mkdocstrings_handlers/python/templates/readthedocs/return.html
mkdocstrings_python_legacy-0.2.7.dist-info/METADATA
mkdocstrings_python_legacy-0.2.7.dist-info/WHEEL
mkdocstrings_python_legacy-0.2.7.dist-info/entry_points.txt
mkdocstrings_python_legacy-0.2.7.dist-info/licenses/LICENSE
mkdocstrings_python_legacy-0.2.7.dist-info/RECORD
