Metadata-Version: 2.4
Name: mkdocstrings-python-legacy
Version: 0.2.7
Summary: A legacy Python handler for mkdocstrings.
Author-Email: =?utf-8?q?Timoth=C3=A9e_Mazzucotelli?= <dev@pawamoy.fr>
License-Expression: ISC
License-File: LICENSE
Classifier: Development Status :: 4 - Beta
Classifier: Intended Audience :: Developers
Classifier: Programming Language :: Python
Classifier: Programming Language :: Python :: 3
Classifier: Programming Language :: Python :: 3 :: Only
Classifier: Programming Language :: Python :: 3.9
Classifier: Programming Language :: Python :: 3.10
Classifier: Programming Language :: Python :: 3.11
Classifier: Programming Language :: Python :: 3.12
Classifier: Programming Language :: Python :: 3.13
Classifier: Programming Language :: Python :: 3.14
Classifier: Topic :: Documentation
Classifier: Topic :: Software Development
Classifier: Topic :: Utilities
Classifier: Typing :: Typed
Project-URL: Homepage, https://mkdocstrings.github.io/python-legacy
Project-URL: Documentation, https://mkdocstrings.github.io/python-legacy
Project-URL: Changelog, https://mkdocstrings.github.io/python-legacy/changelog
Project-URL: Repository, https://github.com/mkdocstrings/python-legacy
Project-URL: Issues, https://github.com/mkdocstrings/python-legacy/issues
Project-URL: Discussions, https://github.com/mkdocstrings/python-legacy/discussions
Project-URL: Gitter, https://gitter.im/mkdocstrings/python-legacy
Project-URL: Funding, https://github.com/sponsors/pawamoy
Requires-Python: >=3.9
Requires-Dist: mkdocstrings>=0.28.3
Requires-Dist: mkdocs-autorefs>=1.1
Requires-Dist: pytkdocs>=0.14
